risk_mgmt_platform/__init__.py
risk_mgmt_platform/__main__.py
risk_mgmt_platform/analyzers/__init__.py
risk_mgmt_platform/collectors/__init__.py
risk_mgmt_platform/traders/__init__.py
risk_mgmt_platform-0.0.0.dist-info/METADATA
risk_mgmt_platform-0.0.0.dist-info/WHEEL
risk_mgmt_platform-0.0.0.dist-info/licenses/LICENSE
risk_mgmt_platform-0.0.0.dist-info/RECORD
