Metadata-Version: 2.1
Name: RISK-MGMT-platform
Version: 0.0.0
Summary: An options trading engine
Project-URL: Homepage, https://github.com/RISK-MGMT/public
Project-URL: Bug Tracker, https://github.com/RISK-MGMT/public/issues
License-File: LICENSE
Classifier: Development Status :: 1 - Planning
Classifier: License :: OSI Approved :: MIT License
Classifier: Operating System :: OS Independent
Classifier: Programming Language :: Python :: 3
Classifier: Topic :: Office/Business :: Financial :: Investment
Requires-Python: >=3.9
